genling/__init__.py
genling-1.0.0.dist-info/METADATA
genling-1.0.0.dist-info/RECORD
genling-1.0.0.dist-info/WHEEL
genling-1.0.0.dist-info/top_level.txt
