Metadata-Version: 2.1
Name: genling
Version: 1.0.0
Summary: Generatrum Linguarum, a conlang word generator library
Home-page: https://github.com/2sh/genling
Author: Seán Hewitt
Author-email: contact@2sh.me
License: UNKNOWN
Platform: UNKNOWN
Classifier: Programming Language :: Python :: 3
Classifier: License :: OSI Approved :: GNU General Public License v3 or later (GPLv3+)
Classifier: Operating System :: OS Independent
Requires-Python: >=3
